ghmdlib/__init__.py
ghmdlib/ghmd.py
ghmdlib/libs/__init__.py
ghmdlib/libs/_download.py
ghmdlib/libs/_offline.py
ghmdlib/libs/_online.py
ghmdlib/libs/_version.py
ghmdlib/libs/argparser.py
ghmdlib/libs/changelog.py
ghmdlib/resources/github-markdown-dark.min.css
ghmdlib/resources/github-markdown-light.min.css
ghmdlib/resources/md-template.html
ghmdlib-0.1.0.dist-info/licenses/LICENSE
ghmdlib-0.1.0.dist-info/METADATA
ghmdlib-0.1.0.dist-info/WHEEL
ghmdlib-0.1.0.dist-info/entry_points.txt
ghmdlib-0.1.0.dist-info/top_level.txt
ghmdlib-0.1.0.dist-info/RECORD
