Metadata-Version: 2.4
Name: ghmdlib
Version: 0.1.0
Summary: A Markdown to GitHub-style HTML file conversion utility.
Author-email: The Developers <development@s3dev.uk>
License-Expression: MIT
Project-URL: Documentation, https://ghmdlib.readthedocs.io
Project-URL: Homepage, https://github.com/s3dev/ghmdlib
Project-URL: Repository, https://github.com/s3dev/ghmdlib
Keywords: converter,conversion,github,html,markdown,utility,utilities
Classifier: Development Status :: 4 - Beta
Classifier: Intended Audience :: Developers
Classifier: Intended Audience :: End Users/Desktop
Classifier: Programming Language :: Python :: 3.10
Classifier: Programming Language :: Python :: 3.11
Classifier: Programming Language :: Python :: 3.12
Classifier: Programming Language :: Python :: 3.13
Classifier: Programming Language :: Python :: Implementation :: CPython
Classifier: Operating System :: POSIX :: Linux
Classifier: Operating System :: Microsoft :: Windows
Classifier: Topic :: Software Development
Classifier: Topic :: Software Development :: Libraries
Classifier: Topic :: Text Processing :: Markup :: HTML
Classifier: Topic :: Text Processing :: Markup :: Markdown
Classifier: Topic :: Utilities
Requires-Python: >=3.10
License-File: LICENSE
Requires-Dist: mdtex2html>=1.3.0
Requires-Dist: requests>=2.32.0
Dynamic: license-file
